ara/api/__init__.py
ara/api/admin.py
ara/api/apps.py
ara/api/auth.py
ara/api/fields.py
ara/api/filters.py
ara/api/models.py
ara/api/renderers.py
ara/api/serializers.py
ara/api/urls.py
ara/api/views.py
ara/api/management/commands/prune.py
ara/api/migrations/0001_initial.py
ara/api/migrations/0002_remove_host_alias.py
ara/api/migrations/0003_add_missing_result_properties.py
ara/api/migrations/0004_duration_in_database.py
ara/api/migrations/0005_unique_label_names.py
ara/api/migrations/0006_remove_result_statuses.py
ara/api/migrations/0007_add_expired_status.py
ara/api/migrations/0008_playbook_controller.py
ara/api/migrations/0009_latesthost.py
ara/api/migrations/0010_result_delegated_to.py
ara/api/migrations/0011_play_label_name_max_length.py
ara/api/migrations/0012_playbook_user.py
ara/api/migrations/0013_task_status.py
ara/api/migrations/0014_ara_versions.py
ara/api/migrations/0015_task_uuid.py
ara/api/migrations/0016_revert_play_label_name_length.py
ara/api/migrations/0017_optional_playbook_controller.py
ara/api/migrations/__init__.py
ara/api/tests/__init__.py
ara/api/tests/factories.py
ara/api/tests/tests_auth.py
ara/api/tests/tests_file.py
ara/api/tests/tests_file_content.py
ara/api/tests/tests_host.py
ara/api/tests/tests_label.py
ara/api/tests/tests_latesthost.py
ara/api/tests/tests_play.py
ara/api/tests/tests_playbook.py
ara/api/tests/tests_prune.py
ara/api/tests/tests_records.py
ara/api/tests/tests_result.py
ara/api/tests/tests_task.py
ara/api/tests/tests_utils.py
ara/api/tests/utils.py
ara/cli/__init__.py
ara/cli/base.py
ara/cli/expire.py
ara/cli/host.py
ara/cli/play.py
ara/cli/playbook.py
ara/cli/record.py
ara/cli/result.py
ara/cli/task.py
ara/cli/utils.py
ara/clients/__init__.py
ara/clients/http.py
ara/clients/offline.py
ara/clients/utils.py
ara/plugins/action/ara_playbook.py
ara/plugins/action/ara_record.py
ara/plugins/callback/ara_default.py
ara/plugins/lookup/ara_api.py
ara/server/__init__.py
ara/server/__main__.py
ara/server/admin.py
ara/server/apps.py
ara-1.7.2.dist-info/LICENSE
ara-1.7.2.dist-info/METADATA
ara-1.7.2.dist-info/WHEEL
ara-1.7.2.dist-info/entry_points.txt
ara-1.7.2.dist-info/pbr.json
ara-1.7.2.dist-info/top_level.txt
ara-1.7.2.dist-info/RECORD
