Metadata-Version: 2.1
Name: ara
Version: 1.7.2
Summary: ARA Records Ansible
Home-page: https://github.com/ansible-community/ara
Author: ARA Records Ansible Authors
Classifier: Intended Audience :: Information Technology
Classifier: Intended Audience :: System Administrators
Classifier: Intended Audience :: Developers
Classifier: Topic :: Utilities
Classifier: License :: OSI Approved :: GNU General Public License v3 (GPLv3)
Classifier: Operating System :: POSIX :: Linux
Classifier: Programming Language :: Python
Classifier: Programming Language :: Python :: 3
Classifier: Programming Language :: Python :: 3.8
Classifier: Programming Language :: Python :: 3.9
Classifier: Programming Language :: Python :: 3.10
Classifier: Programming Language :: Python :: 3.11
Classifier: Programming Language :: Python :: 3.12
Classifier: Development Status :: 5 - Production/Stable
Requires-Python: >=3.8
License-File: LICENSE
Requires-Dist: pbr!=2.1.0,>=2.0.0
Requires-Dist: cliff
Requires-Dist: requests>=2.14.2
Provides-Extra: server
Requires-Dist: Django<4.3,>=3.2; extra == "server"
Requires-Dist: djangorestframework>=3.9.1; extra == "server"
Requires-Dist: django-cors-headers; extra == "server"
Requires-Dist: django-filter; extra == "server"
Requires-Dist: django-health-check; extra == "server"
Requires-Dist: dynaconf[yaml]!=3.1.3,<4.0.0,>=3.0.0; extra == "server"
Requires-Dist: ruamel.yaml; extra == "server"
Requires-Dist: tzlocal>=4.0; extra == "server"
Requires-Dist: whitenoise; extra == "server"
Requires-Dist: pygments; extra == "server"
Provides-Extra: postgresql
Requires-Dist: psycopg2; extra == "postgresql"
Provides-Extra: mysql
Requires-Dist: mysqlclient; extra == "mysql"
Provides-Extra: test
Requires-Dist: factory-boy; extra == "test"
Requires-Dist: bandit>=1.1.0; extra == "test"
Requires-Dist: coverage; extra == "test"
Requires-Dist: flake8; extra == "test"
Requires-Dist: black; extra == "test"
Requires-Dist: isort; extra == "test"
